MANIFEST.in
setup.py
social_auth_py.egg-info/PKG-INFO
social_auth_py.egg-info/SOURCES.txt
social_auth_py.egg-info/dependency_links.txt
social_auth_py.egg-info/not-zip-safe
social_auth_py.egg-info/requires.txt
social_auth_py.egg-info/top_level.txt
socialauth/__init__.py
socialauth/fb.py
socialauth/middleware.py
socialauth/openid_.py
socialauth/twitter.py
socialauth/utils.py
static/css/style.css
static/img/balloon.png
static/img/blogger.png
static/img/claimid.png
static/img/facebook-logo.jpg
static/img/facebook.png
static/img/flickr.png
static/img/google.gif
static/img/indicator.gif
static/img/livejournal.png
static/img/myopenid.png
static/img/myspace.png
static/img/openid.png
static/img/orange.png
static/img/technorati.png
static/img/twitter.png
static/img/verisign.png
static/img/vidoop.png
static/img/wordpress.png
static/img/yahoo.gif
static/js/jquery-1.4.4.min.js
static/js/selector.js
static/js/signin.js