Metadata-Version: 1.0
Name: social-auth-py
Version: 0.0.1
Summary: Authentication middleware for various identity providers
Home-page: https://github.com/AF83/social_auth_py
Author: Pierre Ruyssen (AF83)
Author-email: pierre@ruyssen.fr
License: UNKNOWN
Platform: UNKNOWN
